AUTHORS.txt
CHANGES.txt
MANIFEST.in
README.txt
compile-closure.sh
demo-closure-compiled.html
demo-closure.html
demo-mootools.html
demo-prototype.html
demo-ru.html
demo-uk.html
demo-zh_CN.html
demo.html
generate-sprite.js
generate-sprite.rb
generate-sprite.sh
remcomments.sed
setup.py
css/openid-shadow.css
css/openid.css
images/openid-inputicon.gif
images/openid-providers-en.png
images/openid-providers-ru.png
images.large/aol.gif
images.large/facebook.gif
images.large/google.gif
images.large/linkedin.gif
images.large/mailru.gif
images.large/myopenid.gif
images.large/openid.gif
images.large/rambler.gif
images.large/twitter.gif
images.large/verisign.gif
images.large/vkontakte.gif
images.large/winliveid.gif
images.large/yahoo.gif
images.large/yandex.gif
images.small/aol.ico
images.small/aol.ico.gif
images.small/aol.ico.png
images.small/bitbucket.ico
images.small/bitbucket.ico.gif
images.small/bitbucket.ico.png
images.small/blogger.ico
images.small/blogger.ico.gif
images.small/blogger.ico.png
images.small/claimid.ico
images.small/claimid.ico.gif
images.small/claimid.ico.png
images.small/clickpass.ico
images.small/clickpass.ico.gif
images.small/clickpass.ico.png
images.small/facebook.ico
images.small/facebook.ico.gif
images.small/facebook.ico.png
images.small/flickr.ico
images.small/flickr.ico.gif
images.small/flickr.ico.png
images.small/github.ico
images.small/github.ico.gif
images.small/github.ico.png
images.small/google.ico
images.small/google.ico.gif
images.small/google.ico.png
images.small/google_profile.ico
images.small/google_profile.ico.gif
images.small/google_profile.ico.png
images.small/launchpad.ico
images.small/launchpad.ico.gif
images.small/launchpad.ico.png
images.small/linkedin.ico
images.small/linkedin.ico.gif
images.small/linkedin.ico.png
images.small/livejournal.ico
images.small/livejournal.ico.gif
images.small/livejournal.ico.png
images.small/mailru.ico
images.small/mailru.ico.gif
images.small/mailru.ico.png
images.small/myopenid.ico
openid_selector.egg-info/PKG-INFO
openid_selector.egg-info/SOURCES.txt
openid_selector.egg-info/dependency_links.txt
openid_selector.egg-info/not-zip-safe
openid_selector.egg-info/top_level.txt
