Metadata-Version: 1.1
Name: openid-selector
Version: 0.2
Summary: openid-selector is a frontend in JavaScript for authentication with OpenID, OAuth2, etc
Home-page: http://openid-selector.readthedocs.org
Author: Richard Gomes
Author-email: rgomes.info@gmail.com
License: BSD
Keywords: authentication frontend javascript openid oauth2
Platform: UNKNOWN
Classifier: Programming Language :: JavaScript
Classifier: Topic :: Internet :: WWW/HTTP
